ciso8601.cpython-310-aarch64-linux-gnu.so
ciso8601/__init__.pyi
ciso8601/py.typed
ciso8601-2.3.3.dist-info/METADATA
ciso8601-2.3.3.dist-info/WHEEL
ciso8601-2.3.3.dist-info/top_level.txt
ciso8601-2.3.3.dist-info/RECORD
ciso8601-2.3.3.dist-info/licenses/LICENSE
